posthog/__init__.py
posthog/client.py
posthog/consumer.py
posthog/feature_flags.py
posthog/poller.py
posthog/request.py
posthog/utils.py
posthog/version.py
posthog/sentry/__init__.py
posthog/sentry/django.py
posthog/sentry/posthog_integration.py
posthog/test/__init__.py
posthog/test/test_client.py
posthog/test/test_consumer.py
posthog/test/test_feature_flags.py
posthog/test/test_module.py
posthog/test/test_request.py
posthog/test/test_utils.py
ablaevent-3.0.1.dist-info/LICENSE
ablaevent-3.0.1.dist-info/METADATA
ablaevent-3.0.1.dist-info/WHEEL
ablaevent-3.0.1.dist-info/top_level.txt
ablaevent-3.0.1.dist-info/RECORD
