Metadata-Version: 2.1
Name: ablaevent
Version: 3.0.1
Summary: Integrate PostHog into any python application.
Home-page: https://github.com/posthog/posthog-python
Author: Posthog
Author-email: hey@posthog.com
Maintainer: PostHog
Maintainer-email: hey@posthog.com
License: MIT License
Platform: UNKNOWN
Classifier: Development Status :: 5 - Production/Stable
Classifier: Intended Audience :: Developers
Classifier: License :: OSI Approved :: MIT License
Classifier: Operating System :: OS Independent
Classifier: Programming Language :: Python
Classifier: Programming Language :: Python :: 2
Classifier: Programming Language :: Python :: 2.6
Classifier: Programming Language :: Python :: 2.7
Classifier: Programming Language :: Python :: 3
Classifier: Programming Language :: Python :: 3.2
Classifier: Programming Language :: Python :: 3.3
Classifier: Programming Language :: Python :: 3.4
Classifier: Programming Language :: Python :: 3.5
Classifier: Programming Language :: Python :: 3.6
Classifier: Programming Language :: Python :: 3.7
Classifier: Programming Language :: Python :: 3.8
Requires-Dist: requests (<3.0,>=2.7)
Requires-Dist: six (>=1.5)
Requires-Dist: monotonic (>=1.5)
Requires-Dist: backoff (>=1.10.0)
Requires-Dist: python-dateutil (>2.1)
Provides-Extra: dev
Requires-Dist: black ; extra == 'dev'
Requires-Dist: isort ; extra == 'dev'
Requires-Dist: flake8 ; extra == 'dev'
Requires-Dist: flake8-print ; extra == 'dev'
Requires-Dist: pre-commit ; extra == 'dev'
Provides-Extra: sentry
Requires-Dist: sentry-sdk ; extra == 'sentry'
Requires-Dist: django ; extra == 'sentry'
Provides-Extra: test
Requires-Dist: mock (>=2.0.0) ; extra == 'test'
Requires-Dist: freezegun (==0.3.15) ; extra == 'test'
Requires-Dist: pylint ; extra == 'test'
Requires-Dist: flake8 ; extra == 'test'
Requires-Dist: coverage ; extra == 'test'
Requires-Dist: pytest ; extra == 'test'
